{
  "legislative_session": "221",
  "identifier": "S1069",
  "title": "Establishes county veteran transportation grant program; removes certain restrictions to the current veterans transportation assistance program; appropriates $2 million.*",
  "from_organization": "~{\"classification\": \"upper\"}",
  "classification": [
    "bill"
  ],
  "subject": [
    "TRANSPORT",
    "VETERANS"
  ],
  "abstracts": [],
  "other_titles": [],
  "other_identifiers": [],
  "actions": [
    {
      "description": "Introduced in the Senate, Referred to Senate Military and Veterans' Affairs Committee",
      "date": "2024-01-09T05:00:00+00:00",
      "organization_id": "~{\"classification\": \"upper\"}",
      "classification": [
        "introduction",
        "referral-committee"
      ],
      "related_entities": [],
      "_processing": {
        "log_file_created": "2025-10-25T02:59:24Z"
      }
    },
    {
      "description": "Reported out of Senate Committee with Amendments, 2nd Reading",
      "date": "2024-02-08T05:00:00+00:00",
      "organization_id": "~{\"classification\": \"upper\"}",
      "classification": [
        "committee-passage"
      ],
      "related_entities": [],
      "_processing": {
        "log_file_created": "2025-10-25T02:59:24Z"
      }
    },
    {
      "description": "Referred to Senate Budget and Appropriations Committee",
      "date": "2024-02-08T05:00:00+00:00",
      "organization_id": "~{\"classification\": \"upper\"}",
      "classification": [
        "referral-committee"
      ],
      "related_entities": [],
      "_processing": {
        "log_file_created": "2025-10-25T02:59:24Z"
      }
    }
  ],
  "sponsorships": [
    {
      "name": "Greenstein, Linda R.",
      "classification": "primary",
      "entity_type": "person",
      "primary": true,
      "person_id": "~{\"name\": \"Greenstein, Linda R.\"}",
      "organization_id": null
    },
    {
      "name": "Lagana, Joseph A.",
      "classification": "primary",
      "entity_type": "person",
      "primary": true,
      "person_id": "~{\"name\": \"Lagana, Joseph A.\"}",
      "organization_id": null
    },
    {
      "name": "Bucco, Anthony M.",
      "classification": "cosponsor",
      "entity_type": "person",
      "primary": false,
      "person_id": "~{\"name\": \"Bucco, Anthony M.\"}",
      "organization_id": null
    },
    {
      "name": "Cruz-Perez, Nilsa I.",
      "classification": "cosponsor",
      "entity_type": "person",
      "primary": false,
      "person_id": "~{\"name\": \"Cruz-Perez, Nilsa I.\"}",
      "organization_id": null
    },
    {
      "name": "Space, Parker",
      "classification": "cosponsor",
      "entity_type": "person",
      "primary": false,
      "person_id": "~{\"name\": \"Space, Parker\"}",
      "organization_id": null
    },
    {
      "name": "Amato, Carmen F.",
      "classification": "cosponsor",
      "entity_type": "person",
      "primary": false,
      "person_id": "~{\"name\": \"Amato, Carmen F.\"}",
      "organization_id": null
    }
  ],
  "related_bills": [
    {
      "identifier": "A 518",
      "legislative_session": "221",
      "relation_type": "companion"
    }
  ],
  "versions": [
    {
      "note": "Introduced Version",
      "links": [
        {
          "url": "https://pub.njleg.state.nj.us/Bills/2024/S1500/1069_I1.HTM",
          "media_type": "text/html"
        },
        {
          "url": "https://pub.njleg.state.nj.us/Bills/2024/S1500/1069_I1.PDF",
          "media_type": "application/pdf"
        }
      ],
      "date": "",
      "classification": ""
    },
    {
      "note": "Reprint SMV 2/8/24 1R",
      "links": [
        {
          "url": "https://pub.njleg.state.nj.us/Bills/2024/S1500/1069_R1.HTM",
          "media_type": "text/html"
        },
        {
          "url": "https://pub.njleg.state.nj.us/Bills/2024/S1500/1069_R1.PDF",
          "media_type": "application/pdf"
        }
      ],
      "date": "",
      "classification": ""
    }
  ],
  "documents": [
    {
      "note": "Statement SMV 2/8/24",
      "links": [
        {
          "url": "https://pub.njleg.state.nj.us/Bills/2024/S1500/1069_S1.HTM",
          "media_type": ""
        }
      ],
      "date": "",
      "classification": ""
    }
  ],
  "citations": [],
  "sources": [
    {
      "url": "https://www.njleg.state.nj.us/bill-search/2024/S1069",
      "note": ""
    },
    {
      "url": "https://www.njleg.state.nj.us/bill-search/2024/S1069",
      "note": ""
    },
    {
      "url": "https://www.njleg.state.nj.us/bill-search/2024/S1069",
      "note": ""
    },
    {
      "url": "https://pub.njleg.state.nj.us/leg-databases/",
      "note": ""
    }
  ],
  "extras": {},
  "jurisdiction": {
    "id": "ocd-jurisdiction/country:us/state:nj/government",
    "name": "New Jersey",
    "classification": "state",
    "division_id": "ocd-division/country:us/state:nj"
  },
  "_processing": {
    "logs_latest_update": "2025-10-25T02:59:24Z"
  }
}