{
  "legislative_session": "221",
  "identifier": "SCR81",
  "title": "Proposes constitutional amendment to increase amount of veterans' property tax deduction from $250 to $2,500 over four years.",
  "from_organization": "~{\"classification\": \"upper\"}",
  "classification": [
    "concurrent resolution"
  ],
  "subject": [
    "CONSTITUTION",
    "PROPERTY TAX",
    "VETERANS"
  ],
  "abstracts": [],
  "other_titles": [],
  "other_identifiers": [],
  "actions": [
    {
      "description": "Introduced in the Senate, Referred to Senate Community and Urban Affairs Committee",
      "date": "2024-01-29T05:00:00+00:00",
      "organization_id": "~{\"classification\": \"upper\"}",
      "classification": [
        "introduction",
        "referral-committee"
      ],
      "related_entities": [],
      "_processing": {
        "log_file_created": "2025-10-25T02:59:23Z"
      }
    },
    {
      "description": "Reported out of Senate Committee, 2nd Reading",
      "date": "2024-06-17T04:00:00+00:00",
      "organization_id": "~{\"classification\": \"upper\"}",
      "classification": [
        "committee-passage"
      ],
      "related_entities": [],
      "_processing": {
        "log_file_created": "2025-10-25T02:59:23Z"
      }
    },
    {
      "description": "Referred to Senate Budget and Appropriations Committee",
      "date": "2024-06-17T04:00:00+00:00",
      "organization_id": "~{\"classification\": \"upper\"}",
      "classification": [
        "referral-committee"
      ],
      "related_entities": [],
      "_processing": {
        "log_file_created": "2025-10-25T02:59:23Z"
      }
    }
  ],
  "sponsorships": [
    {
      "name": "Singleton, Troy",
      "classification": "primary",
      "entity_type": "person",
      "primary": true,
      "person_id": "~{\"name\": \"Singleton, Troy\"}",
      "organization_id": null
    },
    {
      "name": "Cruz-Perez, Nilsa I.",
      "classification": "primary",
      "entity_type": "person",
      "primary": true,
      "person_id": "~{\"name\": \"Cruz-Perez, Nilsa I.\"}",
      "organization_id": null
    },
    {
      "name": "Amato, Carmen F.",
      "classification": "cosponsor",
      "entity_type": "person",
      "primary": false,
      "person_id": "~{\"name\": \"Amato, Carmen F.\"}",
      "organization_id": null
    },
    {
      "name": "Bucco, Anthony M.",
      "classification": "cosponsor",
      "entity_type": "person",
      "primary": false,
      "person_id": "~{\"name\": \"Bucco, Anthony M.\"}",
      "organization_id": null
    },
    {
      "name": "Diegnan, Patrick J.",
      "classification": "cosponsor",
      "entity_type": "person",
      "primary": false,
      "person_id": "~{\"name\": \"Diegnan, Patrick J.\"}",
      "organization_id": null
    },
    {
      "name": "O'Scanlon, Declan J.",
      "classification": "cosponsor",
      "entity_type": "person",
      "primary": false,
      "person_id": "~{\"name\": \"O'Scanlon, Declan J.\"}",
      "organization_id": null
    },
    {
      "name": "Ruiz, M. Teresa",
      "classification": "cosponsor",
      "entity_type": "person",
      "primary": false,
      "person_id": "~{\"name\": \"Ruiz, M. Teresa\"}",
      "organization_id": null
    },
    {
      "name": "Schepisi, Holly T.",
      "classification": "cosponsor",
      "entity_type": "person",
      "primary": false,
      "person_id": "~{\"name\": \"Schepisi, Holly T.\"}",
      "organization_id": null
    },
    {
      "name": "Singer, Robert W.",
      "classification": "cosponsor",
      "entity_type": "person",
      "primary": false,
      "person_id": "~{\"name\": \"Singer, Robert W.\"}",
      "organization_id": null
    },
    {
      "name": "Turner, Shirley K.",
      "classification": "cosponsor",
      "entity_type": "person",
      "primary": false,
      "person_id": "~{\"name\": \"Turner, Shirley K.\"}",
      "organization_id": null
    },
    {
      "name": "Zwicker, Andrew",
      "classification": "cosponsor",
      "entity_type": "person",
      "primary": false,
      "person_id": "~{\"name\": \"Zwicker, Andrew\"}",
      "organization_id": null
    },
    {
      "name": "Gopal, Vin",
      "classification": "cosponsor",
      "entity_type": "person",
      "primary": false,
      "person_id": "~{\"name\": \"Gopal, Vin\"}",
      "organization_id": null
    },
    {
      "name": "Space, Parker",
      "classification": "cosponsor",
      "entity_type": "person",
      "primary": false,
      "person_id": "~{\"name\": \"Space, Parker\"}",
      "organization_id": null
    },
    {
      "name": "Tiver, Latham",
      "classification": "cosponsor",
      "entity_type": "person",
      "primary": false,
      "person_id": "~{\"name\": \"Tiver, Latham\"}",
      "organization_id": null
    },
    {
      "name": "Steinhardt, Douglas J.",
      "classification": "cosponsor",
      "entity_type": "person",
      "primary": false,
      "person_id": "~{\"name\": \"Steinhardt, Douglas J.\"}",
      "organization_id": null
    },
    {
      "name": "Polistina, Vincent J.",
      "classification": "cosponsor",
      "entity_type": "person",
      "primary": false,
      "person_id": "~{\"name\": \"Polistina, Vincent J.\"}",
      "organization_id": null
    },
    {
      "name": "Cryan, Joseph P.",
      "classification": "cosponsor",
      "entity_type": "person",
      "primary": false,
      "person_id": "~{\"name\": \"Cryan, Joseph P.\"}",
      "organization_id": null
    },
    {
      "name": "Greenstein, Linda R.",
      "classification": "cosponsor",
      "entity_type": "person",
      "primary": false,
      "person_id": "~{\"name\": \"Greenstein, Linda R.\"}",
      "organization_id": null
    },
    {
      "name": "Holzapfel, James W.",
      "classification": "cosponsor",
      "entity_type": "person",
      "primary": false,
      "person_id": "~{\"name\": \"Holzapfel, James W.\"}",
      "organization_id": null
    }
  ],
  "related_bills": [
    {
      "identifier": "ACR 58",
      "legislative_session": "221",
      "relation_type": "companion"
    }
  ],
  "versions": [
    {
      "note": "Introduced Version",
      "links": [
        {
          "url": "https://pub.njleg.state.nj.us/Bills/2024/SCR/81_I1.HTM",
          "media_type": "text/html"
        },
        {
          "url": "https://pub.njleg.state.nj.us/Bills/2024/SCR/81_I1.PDF",
          "media_type": "application/pdf"
        }
      ],
      "date": "",
      "classification": ""
    }
  ],
  "documents": [
    {
      "note": "Legislative Fiscal Estimate 8/6/2024; as introduced",
      "links": [
        {
          "url": "https://pub.njleg.state.nj.us/Bills/2024/SCR/81_E1.HTM",
          "media_type": ""
        }
      ],
      "date": "",
      "classification": ""
    },
    {
      "note": "Statement SCU 6/17/24",
      "links": [
        {
          "url": "https://pub.njleg.state.nj.us/Bills/2024/SCR/81_S1.HTM",
          "media_type": ""
        }
      ],
      "date": "",
      "classification": ""
    }
  ],
  "citations": [],
  "sources": [
    {
      "url": "https://www.njleg.state.nj.us/bill-search/2024/SCR81",
      "note": ""
    },
    {
      "url": "https://www.njleg.state.nj.us/bill-search/2024/SCR81",
      "note": ""
    },
    {
      "url": "https://www.njleg.state.nj.us/bill-search/2024/SCR81",
      "note": ""
    },
    {
      "url": "https://pub.njleg.state.nj.us/leg-databases/",
      "note": ""
    }
  ],
  "extras": {},
  "jurisdiction": {
    "id": "ocd-jurisdiction/country:us/state:nj/government",
    "name": "New Jersey",
    "classification": "state",
    "division_id": "ocd-division/country:us/state:nj"
  },
  "_processing": {
    "logs_latest_update": "2025-10-25T02:59:23Z",
    "text_extraction_latest_update": "2025-10-25T11:38:55.768446Z"
  }
}