{
  "legislative_session": "221",
  "identifier": "A1672",
  "title": "Makes disabled persons receiving disability payments pursuant to federal Railroad Retirement Act eligible to receive homestead property tax reimbursement.",
  "from_organization": "~{\"classification\": \"lower\"}",
  "classification": [
    "bill"
  ],
  "subject": [
    "DISABLED",
    "PROPERTY TAX"
  ],
  "abstracts": [],
  "other_titles": [],
  "other_identifiers": [],
  "actions": [
    {
      "description": "Introduced in the Assembly, Referred to Assembly Housing Committee",
      "date": "2024-01-09T05:00:00+00:00",
      "organization_id": "~{\"classification\": \"lower\"}",
      "classification": [
        "introduction",
        "referral-committee"
      ],
      "related_entities": [],
      "_processing": {
        "log_file_created": "2025-10-25T02:59:25Z"
      }
    },
    {
      "description": "Reported and Referred to Assembly Appropriations Committee",
      "date": "2024-05-13T04:00:00+00:00",
      "organization_id": "~{\"classification\": \"lower\"}",
      "classification": [
        "referral-committee"
      ],
      "related_entities": [],
      "_processing": {
        "log_file_created": "2025-10-25T02:59:25Z"
      }
    },
    {
      "description": "Reported out of Assembly Committee, 2nd Reading",
      "date": "2024-06-24T04:00:00+00:00",
      "organization_id": "~{\"classification\": \"lower\"}",
      "classification": [
        "committee-passage"
      ],
      "related_entities": [],
      "_processing": {
        "log_file_created": "2025-10-25T02:59:25Z"
      }
    },
    {
      "description": "Passed Assembly (77-0-0)",
      "date": "2024-06-28T04:00:00+00:00",
      "organization_id": "~{\"classification\": \"lower\"}",
      "classification": [
        "passage"
      ],
      "related_entities": [],
      "_processing": {
        "log_file_created": "2025-10-25T02:59:25Z"
      }
    },
    {
      "description": "Received in the Senate, Referred to Senate State Government, Wagering, Tourism & Historic Preservation Committee",
      "date": "2024-09-19T04:00:00+00:00",
      "organization_id": "~{\"classification\": \"upper\"}",
      "classification": [
        "referral-committee"
      ],
      "related_entities": [],
      "_processing": {
        "log_file_created": "2025-10-25T02:59:25Z"
      }
    },
    {
      "description": "Reported out of Senate Committee, 2nd Reading",
      "date": "2024-10-24T04:00:00+00:00",
      "organization_id": "~{\"classification\": \"upper\"}",
      "classification": [
        "committee-passage"
      ],
      "related_entities": [],
      "_processing": {
        "log_file_created": "2025-10-25T02:59:25Z"
      }
    },
    {
      "description": "Referred to Senate Budget and Appropriations Committee",
      "date": "2024-10-24T04:00:00+00:00",
      "organization_id": "~{\"classification\": \"upper\"}",
      "classification": [
        "referral-committee"
      ],
      "related_entities": [],
      "_processing": {
        "log_file_created": "2025-10-25T02:59:25Z"
      }
    },
    {
      "description": "Reported out of Senate Committee, 2nd Reading",
      "date": "2024-12-09T05:00:00+00:00",
      "organization_id": "~{\"classification\": \"upper\"}",
      "classification": [
        "committee-passage"
      ],
      "related_entities": [],
      "_processing": {
        "log_file_created": "2025-10-25T02:59:25Z"
      }
    },
    {
      "description": "Substituted for S1285",
      "date": "2025-01-14T05:00:00+00:00",
      "organization_id": "~{\"classification\": \"upper\"}",
      "classification": [],
      "related_entities": [],
      "_processing": {
        "log_file_created": "2025-10-25T02:59:25Z"
      }
    },
    {
      "description": "Passed Senate (Passed Both Houses) (35-0)",
      "date": "2025-01-14T05:00:00+00:00",
      "organization_id": "~{\"classification\": \"upper\"}",
      "classification": [
        "passage"
      ],
      "related_entities": [],
      "_processing": {
        "log_file_created": "2025-10-25T02:59:25Z"
      }
    },
    {
      "description": "Approved P.L.2025, c.24.",
      "date": "2025-03-06T05:00:00+00:00",
      "organization_id": "~{\"classification\": \"executive\"}",
      "classification": [
        "executive-signature"
      ],
      "related_entities": [],
      "_processing": {
        "log_file_created": "2025-10-25T02:59:25Z"
      }
    }
  ],
  "sponsorships": [
    {
      "name": "Lampitt, Pamela R.",
      "classification": "primary",
      "entity_type": "person",
      "primary": true,
      "person_id": "~{\"name\": \"Lampitt, Pamela R.\"}",
      "organization_id": null
    },
    {
      "name": "Karabinchak, Robert J.",
      "classification": "primary",
      "entity_type": "person",
      "primary": true,
      "person_id": "~{\"name\": \"Karabinchak, Robert J.\"}",
      "organization_id": null
    },
    {
      "name": "Hutchison, Dan",
      "classification": "primary",
      "entity_type": "person",
      "primary": true,
      "person_id": "~{\"name\": \"Hutchison, Dan\"}",
      "organization_id": null
    },
    {
      "name": "Beach, James",
      "classification": "primary",
      "entity_type": "person",
      "primary": true,
      "person_id": "~{\"name\": \"Beach, James\"}",
      "organization_id": null
    },
    {
      "name": "Mukherji, Raj",
      "classification": "primary",
      "entity_type": "person",
      "primary": true,
      "person_id": "~{\"name\": \"Mukherji, Raj\"}",
      "organization_id": null
    },
    {
      "name": "Fantasia, Dawn",
      "classification": "cosponsor",
      "entity_type": "person",
      "primary": false,
      "person_id": "~{\"name\": \"Fantasia, Dawn\"}",
      "organization_id": null
    },
    {
      "name": "Miller, Cody D.",
      "classification": "cosponsor",
      "entity_type": "person",
      "primary": false,
      "person_id": "~{\"name\": \"Miller, Cody D.\"}",
      "organization_id": null
    },
    {
      "name": "Inganamort, Michael",
      "classification": "cosponsor",
      "entity_type": "person",
      "primary": false,
      "person_id": "~{\"name\": \"Inganamort, Michael\"}",
      "organization_id": null
    },
    {
      "name": "Bagolie, Rosaura",
      "classification": "cosponsor",
      "entity_type": "person",
      "primary": false,
      "person_id": "~{\"name\": \"Bagolie, Rosaura\"}",
      "organization_id": null
    },
    {
      "name": "Speight, Shanique",
      "classification": "cosponsor",
      "entity_type": "person",
      "primary": false,
      "person_id": "~{\"name\": \"Speight, Shanique\"}",
      "organization_id": null
    },
    {
      "name": "Diegnan, Patrick J.",
      "classification": "cosponsor",
      "entity_type": "person",
      "primary": false,
      "person_id": "~{\"name\": \"Diegnan, Patrick J.\"}",
      "organization_id": null
    },
    {
      "name": "McKeon, John F.",
      "classification": "cosponsor",
      "entity_type": "person",
      "primary": false,
      "person_id": "~{\"name\": \"McKeon, John F.\"}",
      "organization_id": null
    },
    {
      "name": "Turner, Shirley K.",
      "classification": "cosponsor",
      "entity_type": "person",
      "primary": false,
      "person_id": "~{\"name\": \"Turner, Shirley K.\"}",
      "organization_id": null
    },
    {
      "name": "Space, Parker",
      "classification": "cosponsor",
      "entity_type": "person",
      "primary": false,
      "person_id": "~{\"name\": \"Space, Parker\"}",
      "organization_id": null
    }
  ],
  "related_bills": [
    {
      "identifier": "S 1285",
      "legislative_session": "221",
      "relation_type": "companion"
    }
  ],
  "versions": [
    {
      "note": "Introduced Version",
      "links": [
        {
          "url": "https://pub.njleg.state.nj.us/Bills/2024/A2000/1672_I1.HTM",
          "media_type": "text/html"
        },
        {
          "url": "https://pub.njleg.state.nj.us/Bills/2024/A2000/1672_I1.PDF",
          "media_type": "application/pdf"
        }
      ],
      "date": "",
      "classification": ""
    }
  ],
  "documents": [
    {
      "note": "Legislative Fiscal Estimate 6/26/24; as introduced",
      "links": [
        {
          "url": "https://pub.njleg.state.nj.us/Bills/2024/A2000/1672_E1.HTM",
          "media_type": ""
        }
      ],
      "date": "",
      "classification": ""
    },
    {
      "note": "Statement AHO 5/13/24",
      "links": [
        {
          "url": "https://pub.njleg.state.nj.us/Bills/2024/A2000/1672_S1.HTM",
          "media_type": ""
        }
      ],
      "date": "",
      "classification": ""
    },
    {
      "note": "Statement AAP 6/24/24",
      "links": [
        {
          "url": "https://pub.njleg.state.nj.us/Bills/2024/A2000/1672_S2.HTM",
          "media_type": ""
        }
      ],
      "date": "",
      "classification": ""
    },
    {
      "note": "Statement SSG 10/24/24",
      "links": [
        {
          "url": "https://pub.njleg.state.nj.us/Bills/2024/A2000/1672_S3.HTM",
          "media_type": ""
        }
      ],
      "date": "",
      "classification": ""
    },
    {
      "note": "Statement SBA 12/9/24",
      "links": [
        {
          "url": "https://pub.njleg.state.nj.us/Bills/2024/A2000/1672_S4.HTM",
          "media_type": ""
        }
      ],
      "date": "",
      "classification": ""
    },
    {
      "note": "Technical Report AHO 5/13/24 TR",
      "links": [
        {
          "url": "https://pub.njleg.state.nj.us/Bills/2024/A2000/1672_T1.HTM",
          "media_type": ""
        }
      ],
      "date": "",
      "classification": ""
    },
    {
      "note": "Advance Law",
      "links": [
        {
          "url": "https://pub.njleg.state.nj.us/Bills/2024/AL25/24_.HTM",
          "media_type": ""
        }
      ],
      "date": "",
      "classification": ""
    },
    {
      "note": "Pamphlet Law",
      "links": [
        {
          "url": "https://pub.njleg.state.nj.us/Bills/2024/PL25/24_.HTM",
          "media_type": ""
        }
      ],
      "date": "",
      "classification": ""
    }
  ],
  "citations": [],
  "sources": [
    {
      "url": "https://www.njleg.state.nj.us/bill-search/2024/A1672",
      "note": ""
    },
    {
      "url": "https://www.njleg.state.nj.us/bill-search/2024/A1672",
      "note": ""
    },
    {
      "url": "https://www.njleg.state.nj.us/bill-search/2024/A1672",
      "note": ""
    },
    {
      "url": "https://www.njleg.state.nj.us/bill-search/2024/A1672",
      "note": ""
    },
    {
      "url": "https://www.njleg.state.nj.us/bill-search/2024/A1672",
      "note": ""
    },
    {
      "url": "https://www.njleg.state.nj.us/bill-search/2024/A1672",
      "note": ""
    },
    {
      "url": "https://www.njleg.state.nj.us/bill-search/2024/A1672",
      "note": ""
    },
    {
      "url": "https://www.njleg.state.nj.us/bill-search/2024/A1672",
      "note": ""
    },
    {
      "url": "https://www.njleg.state.nj.us/bill-search/2024/A1672",
      "note": ""
    },
    {
      "url": "https://www.njleg.state.nj.us/bill-search/2024/A1672",
      "note": ""
    },
    {
      "url": "https://www.njleg.state.nj.us/bill-search/2024/A1672",
      "note": ""
    },
    {
      "url": "https://pub.njleg.state.nj.us/leg-databases/",
      "note": ""
    }
  ],
  "extras": {},
  "jurisdiction": {
    "id": "ocd-jurisdiction/country:us/state:nj/government",
    "name": "New Jersey",
    "classification": "state",
    "division_id": "ocd-division/country:us/state:nj"
  },
  "_processing": {
    "logs_latest_update": "2025-10-25T02:59:25Z",
    "text_extraction_latest_update": "2025-10-28T12:26:24.974132Z"
  }
}