{
  "legislative_session": "221",
  "identifier": "SR66",
  "title": "Urges Governor to resume in-person services at DOLWD.",
  "from_organization": "~{\"classification\": \"upper\"}",
  "classification": [
    "resolution"
  ],
  "subject": [
    "GOVERNOR",
    "LABOR",
    "STATE DEPTS"
  ],
  "abstracts": [],
  "other_titles": [],
  "other_identifiers": [],
  "actions": [
    {
      "description": "Introduced in the Senate, Referred to Senate Labor Committee",
      "date": "2024-02-05T05:00:00+00:00",
      "organization_id": "~{\"classification\": \"upper\"}",
      "classification": [
        "introduction",
        "referral-committee"
      ],
      "related_entities": [],
      "_processing": {
        "log_file_created": "2025-10-25T02:59:25Z"
      }
    }
  ],
  "sponsorships": [
    {
      "name": "Bucco, Anthony M.",
      "classification": "primary",
      "entity_type": "person",
      "primary": true,
      "person_id": "~{\"name\": \"Bucco, Anthony M.\"}",
      "organization_id": null
    },
    {
      "name": "Corrado, Kristin M.",
      "classification": "cosponsor",
      "entity_type": "person",
      "primary": false,
      "person_id": "~{\"name\": \"Corrado, Kristin M.\"}",
      "organization_id": null
    },
    {
      "name": "Tiver, Latham",
      "classification": "cosponsor",
      "entity_type": "person",
      "primary": false,
      "person_id": "~{\"name\": \"Tiver, Latham\"}",
      "organization_id": null
    }
  ],
  "related_bills": [],
  "versions": [
    {
      "note": "Introduced Version",
      "links": [
        {
          "url": "https://pub.njleg.state.nj.us/Bills/2024/SR/66_I1.HTM",
          "media_type": "text/html"
        },
        {
          "url": "https://pub.njleg.state.nj.us/Bills/2024/SR/66_I1.PDF",
          "media_type": "application/pdf"
        }
      ],
      "date": "",
      "classification": ""
    }
  ],
  "documents": [],
  "citations": [],
  "sources": [
    {
      "url": "https://www.njleg.state.nj.us/bill-search/2024/SR66",
      "note": ""
    },
    {
      "url": "https://pub.njleg.state.nj.us/leg-databases/",
      "note": ""
    }
  ],
  "extras": {},
  "jurisdiction": {
    "id": "ocd-jurisdiction/country:us/state:nj/government",
    "name": "New Jersey",
    "classification": "state",
    "division_id": "ocd-division/country:us/state:nj"
  },
  "_processing": {
    "logs_latest_update": "2025-10-25T02:59:25Z",
    "text_extraction_latest_update": "2025-10-29T13:03:32.843540Z"
  }
}