{
  "legislative_session": "221",
  "identifier": "A5174",
  "title": "Modifies capital reserve funding requirements for planned real estate developments in certain circumstances.",
  "from_organization": "~{\"classification\": \"lower\"}",
  "classification": [
    "bill"
  ],
  "subject": [
    "ECONOMIC DEV",
    "HOUSING FIN"
  ],
  "abstracts": [],
  "other_titles": [],
  "other_identifiers": [],
  "actions": [
    {
      "description": "Introduced in the Assembly, Referred to Assembly Housing Committee",
      "date": "2025-01-14T05:00:00+00:00",
      "organization_id": "~{\"classification\": \"lower\"}",
      "classification": [
        "introduction",
        "referral-committee"
      ],
      "related_entities": [],
      "_processing": {
        "log_file_created": "2025-10-25T02:59:28Z"
      }
    },
    {
      "description": "Reported out of Assembly Committee, 2nd Reading",
      "date": "2025-02-10T05:00:00+00:00",
      "organization_id": "~{\"classification\": \"lower\"}",
      "classification": [
        "committee-passage"
      ],
      "related_entities": [],
      "_processing": {
        "log_file_created": "2025-10-25T02:59:28Z"
      }
    },
    {
      "description": "Passed Assembly (75-0-0)",
      "date": "2025-02-27T05:00:00+00:00",
      "organization_id": "~{\"classification\": \"lower\"}",
      "classification": [
        "passage"
      ],
      "related_entities": [],
      "_processing": {
        "log_file_created": "2025-10-25T02:59:28Z"
      }
    },
    {
      "description": "Received in the Senate, Referred to Senate Community and Urban Affairs Committee",
      "date": "2025-03-03T05:00:00+00:00",
      "organization_id": "~{\"classification\": \"upper\"}",
      "classification": [
        "referral-committee"
      ],
      "related_entities": [],
      "_processing": {
        "log_file_created": "2025-10-25T02:59:28Z"
      }
    }
  ],
  "sponsorships": [
    {
      "name": "Lopez, Yvonne",
      "classification": "primary",
      "entity_type": "person",
      "primary": true,
      "person_id": "~{\"name\": \"Lopez, Yvonne\"}",
      "organization_id": null
    }
  ],
  "related_bills": [],
  "versions": [
    {
      "note": "Introduced Version",
      "links": [
        {
          "url": "https://pub.njleg.state.nj.us/Bills/2024/A5500/5174_I1.HTM",
          "media_type": "text/html"
        },
        {
          "url": "https://pub.njleg.state.nj.us/Bills/2024/A5500/5174_I1.PDF",
          "media_type": "application/pdf"
        }
      ],
      "date": "",
      "classification": ""
    }
  ],
  "documents": [
    {
      "note": "Statement AHO 2/10/25",
      "links": [
        {
          "url": "https://pub.njleg.state.nj.us/Bills/2024/A5500/5174_S1.HTM",
          "media_type": ""
        }
      ],
      "date": "",
      "classification": ""
    }
  ],
  "citations": [],
  "sources": [
    {
      "url": "https://www.njleg.state.nj.us/bill-search/2024/A5174",
      "note": ""
    },
    {
      "url": "https://www.njleg.state.nj.us/bill-search/2024/A5174",
      "note": ""
    },
    {
      "url": "https://www.njleg.state.nj.us/bill-search/2024/A5174",
      "note": ""
    },
    {
      "url": "https://www.njleg.state.nj.us/bill-search/2024/A5174",
      "note": ""
    },
    {
      "url": "https://pub.njleg.state.nj.us/leg-databases/",
      "note": ""
    }
  ],
  "extras": {},
  "jurisdiction": {
    "id": "ocd-jurisdiction/country:us/state:nj/government",
    "name": "New Jersey",
    "classification": "state",
    "division_id": "ocd-division/country:us/state:nj"
  },
  "_processing": {
    "logs_latest_update": "2025-10-25T02:59:28Z"
  }
}